olap_zhang3/__init__.py
olap_zhang3/olap.py
olap_zhang3-0.0.1.dist-info/LICENSE
olap_zhang3-0.0.1.dist-info/METADATA
olap_zhang3-0.0.1.dist-info/WHEEL
olap_zhang3-0.0.1.dist-info/top_level.txt
olap_zhang3-0.0.1.dist-info/RECORD
