Metadata-Version: 2.1
Name: olap_zhang3
Version: 0.0.1
Summary: 秘密
Author-email: zhang3 <675942084@qq.com>
Project-URL: Homepage, https://github.com/pypa/sampleproject
Project-URL: Issues, https://github.com/pypa/sampleproject/issues
Classifier: Programming Language :: Python :: 3
Classifier: License :: OSI Approved :: MIT License
Classifier: Operating System :: OS Independent
Requires-Python: >=3.8
License-File: LICENSE
